{
  "status": "success",
  "remarks": "",
  "data": [
    {
      "dhanClientId": "1102738431",
      "tradingSymbol": "BANKNIFTY-Apr2024-47500-PE",
      "securityId": "49507",
      "positionType": "CLOSED",
      "exchangeSegment": "NSE_FNO",
      "productType": "MARGIN",
      "buyAvg": 72.95,
      "costPrice": 71.65,
      "buyQty": 75,
      "sellAvg": 59.8,
      "sellQty": 75,
      "netQty": 0,
      "realizedProfit": -986.25,
      "unrealizedProfit": 0.0,
      "rbiReferenceRate": 1.0,
      "multiplier": 1000,
      "carryForwardBuyQty": 75,
      "carryForwardSellQty": 0,
      "carryForwardBuyValue": 5471.25,
      "carryForwardSellValue": 0.0,
      "dayBuyQty": 0,
      "daySellQty": 75,
      "dayBuyValue": 0.0,
      "daySellValue": 4485.0,
      "drvExpiryDate": "2024-04-30",
      "drvOptionType": "PUT",
      "drvStrikePrice": 47500.0,
      "crossCurrency": false
    },
    {
      "dhanClientId": "1102738431",
      "tradingSymbol": "BANKNIFTY-Apr2024-48000-PE",
      "securityId": "49522",
      "positionType": "CLOSED",
      "exchangeSegment": "NSE_FNO",
      "productType": "MARGIN",
      "buyAvg": 194.4,
      "costPrice": 150.65,
      "buyQty": 75,
      "sellAvg": 153.85,
      "sellQty": 75,
      "netQty": 0,
      "realizedProfit": -3041.25,
      "unrealizedProfit": 602.25,
      "rbiReferenceRate": 1.0,
      "multiplier": 1000,
      "carryForwardBuyQty": 0,
      "carryForwardSellQty": 75,
      "carryForwardBuyValue": 0.0,
      "carryForwardSellValue": 11538.75,
      "dayBuyQty": 75,
      "daySellQty": 0,
      "dayBuyValue": 14580.0,
      "daySellValue": 0.0,
      "drvExpiryDate": "2024-04-30",
      "drvOptionType": "PUT",
      "drvStrikePrice": 48000.0,
      "crossCurrency": false
    },
    {
      "dhanClientId": "1102738431",
      "tradingSymbol": "BANKNIFTY-Apr2024-49000-CE",
      "securityId": "49562",
      "positionType": "CLOSED",
      "exchangeSegment": "NSE_FNO",
      "productType": "MARGIN",
      "buyAvg": 53.3,
      "costPrice": 117.3,
      "buyQty": 75,
      "sellAvg": 124.75,
      "sellQty": 75,
      "netQty": 0,
      "realizedProfit": 5358.75,
      "unrealizedProfit": 0.0,
      "rbiReferenceRate": 1.0,
      "multiplier": 1000,
      "carryForwardBuyQty": 0,
      "carryForwardSellQty": 75,
      "carryForwardBuyValue": 0.0,
      "carryForwardSellValue": 9356.25,
      "dayBuyQty": 75,
      "daySellQty": 0,
      "dayBuyValue": 3997.5,
      "daySellValue": 0.0,
      "drvExpiryDate": "2024-04-30",
      "drvOptionType": "CALL",
      "drvStrikePrice": 49000.0,
      "crossCurrency": false
    },
    {
      "dhanClientId": "1102738431",
      "tradingSymbol": "BANKNIFTY-Apr2024-49500-CE",
      "securityId": "49585",
      "positionType": "CLOSED",
      "exchangeSegment": "NSE_FNO",
      "productType": "MARGIN",
      "buyAvg": 37.25,
      "costPrice": 33.9,
      "buyQty": 75,
      "sellAvg": 18.55,
      "sellQty": 75,
      "netQty": 0,
      "realizedProfit": -1402.5,
      "unrealizedProfit": 0.0,
      "rbiReferenceRate": 1.0,
      "multiplier": 1000,
      "carryForwardBuyQty": 75,
      "carryForwardSellQty": 0,
      "carryForwardBuyValue": 2793.75,
      "carryForwardSellValue": 0.0,
      "dayBuyQty": 0,
      "daySellQty": 75,
      "dayBuyValue": 0.0,
      "daySellValue": 1391.25,
      "drvExpiryDate": "2024-04-30",
      "drvOptionType": "CALL",
      "drvStrikePrice": 49500.0,
      "crossCurrency": false
    },
    {
      "dhanClientId": "1102738431",
      "tradingSymbol": "BANKNIFTY-Apr2024-47200-PE",
      "securityId": "49501",
      "positionType": "LONG",
      "exchangeSegment": "NSE_FNO",
      "productType": "MARGIN",
      "buyAvg": 33.075,
      "costPrice": 33.075,
      "buyQty": 150,
      "sellAvg": 32.35,
      "sellQty": 75,
      "netQty": 75,
      "realizedProfit": -54.375,
      "unrealizedProfit": -95.62506,
      "rbiReferenceRate": 1.0,
      "multiplier": 1,
      "carryForwardBuyQty": 0,
      "carryForwardSellQty": 0,
      "carryForwardBuyValue": 0.0,
      "carryForwardSellValue": 0.0,
      "dayBuyQty": 150,
      "daySellQty": 75,
      "dayBuyValue": 4961.25,
      "daySellValue": 2426.25,
      "drvExpiryDate": "2024-04-30 14:30:00",
      "drvOptionType": "PUT",
      "drvStrikePrice": 47200.0,
      "crossCurrency": false
    },
    {
      "dhanClientId": "1102738431",
      "tradingSymbol": "BANKNIFTY-Apr2024-47700-PE",
      "securityId": "49512",
      "positionType": "SHORT",
      "exchangeSegment": "NSE_FNO",
      "productType": "MARGIN",
      "buyAvg": 90.8,
      "costPrice": 90.625,
      "buyQty": 75,
      "sellAvg": 90.625,
      "sellQty": 150,
      "netQty": -75,
      "realizedProfit": -13.125,
      "unrealizedProfit": -568.12476,
      "rbiReferenceRate": 1.0,
      "multiplier": 1,
      "carryForwardBuyQty": 0,
      "carryForwardSellQty": 0,
      "carryForwardBuyValue": 0.0,
      "carryForwardSellValue": 0.0,
      "dayBuyQty": 75,
      "daySellQty": 150,
      "dayBuyValue": 6810.0,
      "daySellValue": 13593.75,
      "drvExpiryDate": "2024-04-30 14:30:00",
      "drvOptionType": "PUT",
      "drvStrikePrice": 47700.0,
      "crossCurrency": false
    },
    {
      "dhanClientId": "1102738431",
      "tradingSymbol": "BANKNIFTY-Apr2024-49200-CE",
      "securityId": "49570",
      "positionType": "LONG",
      "exchangeSegment": "NSE_FNO",
      "productType": "MARGIN",
      "buyAvg": 36.55,
      "costPrice": 36.55,
      "buyQty": 150,
      "sellAvg": 36.63,
      "sellQty": 75,
      "netQty": 75,
      "realizedProfit": 6.0,
      "unrealizedProfit": 224.99994,
      "rbiReferenceRate": 1.0,
      "multiplier": 1,
      "carryForwardBuyQty": 0,
      "carryForwardSellQty": 0,
      "carryForwardBuyValue": 0.0,
      "carryForwardSellValue": 0.0,
      "dayBuyQty": 150,
      "daySellQty": 75,
      "dayBuyValue": 5482.5,
      "daySellValue": 2747.25,
      "drvExpiryDate": "2024-04-30 14:30:00",
      "drvOptionType": "CALL",
      "drvStrikePrice": 49200.0,
      "crossCurrency": false
    },
    {
      "dhanClientId": "1102738431",
      "tradingSymbol": "BANKNIFTY-Apr2024-48700-CE",
      "securityId": "49554",
      "positionType": "SHORT",
      "exchangeSegment": "NSE_FNO",
      "productType": "MARGIN",
      "buyAvg": 123.27,
      "costPrice": 124.625,
      "buyQty": 75,
      "sellAvg": 124.625,
      "sellQty": 150,
      "netQty": -75,
      "realizedProfit": 101.625,
      "unrealizedProfit": 1366.8755,
      "rbiReferenceRate": 1.0,
      "multiplier": 1,
      "carryForwardBuyQty": 0,
      "carryForwardSellQty": 0,
      "carryForwardBuyValue": 0.0,
      "carryForwardSellValue": 0.0,
      "dayBuyQty": 75,
      "daySellQty": 150,
      "dayBuyValue": 9245.25,
      "daySellValue": 18693.75,
      "drvExpiryDate": "2024-04-30 14:30:00",
      "drvOptionType": "CALL",
      "drvStrikePrice": 48700.0,
      "crossCurrency": false
    }
  ]
}
