{
  "status": true,
  "message": "SUCCESS",
  "errorcode": "",
  "data": [
    {
      "symboltoken": "67493",
      "symbolname": "BANKNIFTY",
      "instrumenttype": "OPTIDX",
      "priceden": "1.00",
      "pricenum": "1.00",
      "genden": "1.00",
      "gennum": "1.00",
      "precision": "2",
      "multiplier": "-1",
      "boardlotsize": "1",
      "exchange": "NFO",
      "producttype": "CARRYFORWARD",
      "tradingsymbol": "BANKNIFTY24APR2446300PE",
      "symbolgroup": "XX",
      "strikeprice": "46300.0",
      "optiontype": "PE",
      "expirydate": "24APR2024",
      "lotsize": "15",
      "cfbuyqty": "0",
      "cfsellqty": "0",
      "cfbuyamount": "0.00",
      "cfsellamount": "0.00",
      "buyavgprice": "17.91",
      "sellavgprice": "0.00",
      "avgnetprice": "17.91",
      "netvalue": "-1611.75",
      "netqty": "90",
      "totalbuyvalue": "1611.75",
      "totalsellvalue": "0.00",
      "cfbuyavgprice": "0.00",
      "cfsellavgprice": "0.00",
      "totalbuyavgprice": "17.91",
      "totalsellavgprice": "0.00",
      "netprice": "17.90",
      "buyqty": "90",
      "sellqty": "0",
      "buyamount": "1611.75",
      "sellamount": "0.00",
      "pnl": "26.10",
      "realised": "-0.00",
      "unrealised": "26.10",
      "ltp": "18.2",
      "close": "115.6"
    },
    {
      "symboltoken": "67503",
      "symbolname": "BANKNIFTY",
      "instrumenttype": "OPTIDX",
      "priceden": "1.00",
      "pricenum": "1.00",
      "genden": "1.00",
      "gennum": "1.00",
      "precision": "2",
      "multiplier": "-1",
      "boardlotsize": "1",
      "exchange": "NFO",
      "producttype": "CARRYFORWARD",
      "tradingsymbol": "BANKNIFTY24APR2446800PE",
      "symbolgroup": "XX",
      "strikeprice": "46800.0",
      "optiontype": "PE",
      "expirydate": "24APR2024",
      "lotsize": "15",
      "cfbuyqty": "0",
      "cfsellqty": "0",
      "cfbuyamount": "0.00",
      "cfsellamount": "0.00",
      "buyavgprice": "49.67",
      "sellavgprice": "42.20",
      "avgnetprice": "0.00",
      "netvalue": "-448.50",
      "netqty": "0",
      "totalbuyvalue": "2980.50",
      "totalsellvalue": "2532.00",
      "cfbuyavgprice": "0.00",
      "cfsellavgprice": "0.00",
      "totalbuyavgprice": "49.67",
      "totalsellavgprice": "42.20",
      "netprice": "0.00",
      "buyqty": "60",
      "sellqty": "60",
      "buyamount": "2980.50",
      "sellamount": "2532.00",
      "pnl": "-448.20",
      "realised": "-448.20",
      "unrealised": "0.00",
      "ltp": "32.7",
      "close": "193.85"
    },
    {
      "symboltoken": "67507",
      "symbolname": "BANKNIFTY",
      "instrumenttype": "OPTIDX",
      "priceden": "1.00",
      "pricenum": "1.00",
      "genden": "1.00",
      "gennum": "1.00",
      "precision": "2",
      "multiplier": "-1",
      "boardlotsize": "1",
      "exchange": "NFO",
      "producttype": "CARRYFORWARD",
      "tradingsymbol": "BANKNIFTY24APR2447000PE",
      "symbolgroup": "XX",
      "strikeprice": "47000.0",
      "optiontype": "PE",
      "expirydate": "24APR2024",
      "lotsize": "15",
      "cfbuyqty": "0",
      "cfsellqty": "0",
      "cfbuyamount": "0.00",
      "cfsellamount": "0.00",
      "buyavgprice": "0.00",
      "sellavgprice": "41.95",
      "avgnetprice": "41.95",
      "netvalue": "3775.50",
      "netqty": "-90",
      "totalbuyvalue": "0.00",
      "totalsellvalue": "3775.50",
      "cfbuyavgprice": "0.00",
      "cfsellavgprice": "0.00",
      "totalbuyavgprice": "0.00",
      "totalsellavgprice": "41.95",
      "netprice": "41.95",
      "buyqty": "0",
      "sellqty": "90",
      "buyamount": "0.00",
      "sellamount": "3775.50",
      "pnl": "27.00",
      "realised": "0.00",
      "unrealised": "27.00",
      "ltp": "41.65",
      "close": "238.65"
    },
    {
      "symboltoken": "67513",
      "symbolname": "BANKNIFTY",
      "instrumenttype": "OPTIDX",
      "priceden": "1.00",
      "pricenum": "1.00",
      "genden": "1.00",
      "gennum": "1.00",
      "precision": "2",
      "multiplier": "-1",
      "boardlotsize": "1",
      "exchange": "NFO",
      "producttype": "CARRYFORWARD",
      "tradingsymbol": "BANKNIFTY24APR2447300PE",
      "symbolgroup": "XX",
      "strikeprice": "47300.0",
      "optiontype": "PE",
      "expirydate": "24APR2024",
      "lotsize": "15",
      "cfbuyqty": "0",
      "cfsellqty": "0",
      "cfbuyamount": "0.00",
      "cfsellamount": "0.00",
      "buyavgprice": "95.15",
      "sellavgprice": "113.36",
      "avgnetprice": "0.00",
      "netvalue": "1092.75",
      "netqty": "0",
      "totalbuyvalue": "5709.00",
      "totalsellvalue": "6801.75",
      "cfbuyavgprice": "0.00",
      "cfsellavgprice": "0.00",
      "totalbuyavgprice": "95.15",
      "totalsellavgprice": "113.36",
      "netprice": "0.00",
      "buyqty": "60",
      "sellqty": "60",
      "buyamount": "5709.00",
      "sellamount": "6801.75",
      "pnl": "1092.60",
      "realised": "1092.60",
      "unrealised": "0.00",
      "ltp": "61.55",
      "close": "326.25"
    },
    {
      "symboltoken": "67532",
      "symbolname": "BANKNIFTY",
      "instrumenttype": "OPTIDX",
      "priceden": "1.00",
      "pricenum": "1.00",
      "genden": "1.00",
      "gennum": "1.00",
      "precision": "2",
      "multiplier": "-1",
      "boardlotsize": "1",
      "exchange": "NFO",
      "producttype": "CARRYFORWARD",
      "tradingsymbol": "BANKNIFTY24APR2448300CE",
      "symbolgroup": "XX",
      "strikeprice": "48300.0",
      "optiontype": "CE",
      "expirydate": "24APR2024",
      "lotsize": "15",
      "cfbuyqty": "0",
      "cfsellqty": "0",
      "cfbuyamount": "0.00",
      "cfsellamount": "0.00",
      "buyavgprice": "54.52",
      "sellavgprice": "65.15",
      "avgnetprice": "0.00",
      "netvalue": "2550.00",
      "netqty": "0",
      "totalbuyvalue": "13086.00",
      "totalsellvalue": "15636.00",
      "cfbuyavgprice": "0.00",
      "cfsellavgprice": "0.00",
      "totalbuyavgprice": "54.52",
      "totalsellavgprice": "65.15",
      "netprice": "0.00",
      "buyqty": "240",
      "sellqty": "240",
      "buyamount": "13086.00",
      "sellamount": "15636.00",
      "pnl": "2551.20",
      "realised": "2551.20",
      "unrealised": "-0.00",
      "ltp": "104.1",
      "close": "122.95"
    },
    {
      "symboltoken": "67536",
      "symbolname": "BANKNIFTY",
      "instrumenttype": "OPTIDX",
      "priceden": "1.00",
      "pricenum": "1.00",
      "genden": "1.00",
      "gennum": "1.00",
      "precision": "2",
      "multiplier": "-1",
      "boardlotsize": "1",
      "exchange": "NFO",
      "producttype": "CARRYFORWARD",
      "tradingsymbol": "BANKNIFTY24APR2448500CE",
      "symbolgroup": "XX",
      "strikeprice": "48500.0",
      "optiontype": "CE",
      "expirydate": "24APR2024",
      "lotsize": "15",
      "cfbuyqty": "0",
      "cfsellqty": "0",
      "cfbuyamount": "0.00",
      "cfsellamount": "0.00",
      "buyavgprice": "0.00",
      "sellavgprice": "54.80",
      "avgnetprice": "54.80",
      "netvalue": "4932.00",
      "netqty": "-90",
      "totalbuyvalue": "0.00",
      "totalsellvalue": "4932.00",
      "cfbuyavgprice": "0.00",
      "cfsellavgprice": "0.00",
      "totalbuyavgprice": "0.00",
      "totalsellavgprice": "54.80",
      "netprice": "54.80",
      "buyqty": "0",
      "sellqty": "90",
      "buyamount": "0.00",
      "sellamount": "4932.00",
      "pnl": "198.00",
      "realised": "0.00",
      "unrealised": "198.00",
      "ltp": "52.6",
      "close": "80.8"
    },
    {
      "symboltoken": "67542",
      "symbolname": "BANKNIFTY",
      "instrumenttype": "OPTIDX",
      "priceden": "1.00",
      "pricenum": "1.00",
      "genden": "1.00",
      "gennum": "1.00",
      "precision": "2",
      "multiplier": "-1",
      "boardlotsize": "1",
      "exchange": "NFO",
      "producttype": "CARRYFORWARD",
      "tradingsymbol": "BANKNIFTY24APR2448800CE",
      "symbolgroup": "XX",
      "strikeprice": "48800.0",
      "optiontype": "CE",
      "expirydate": "24APR2024",
      "lotsize": "15",
      "cfbuyqty": "0",
      "cfsellqty": "0",
      "cfbuyamount": "0.00",
      "cfsellamount": "0.00",
      "buyavgprice": "19.40",
      "sellavgprice": "15.55",
      "avgnetprice": "0.00",
      "netvalue": "-231.00",
      "netqty": "0",
      "totalbuyvalue": "1164.00",
      "totalsellvalue": "933.00",
      "cfbuyavgprice": "0.00",
      "cfsellavgprice": "0.00",
      "totalbuyavgprice": "19.40",
      "totalsellavgprice": "15.55",
      "netprice": "0.00",
      "buyqty": "60",
      "sellqty": "60",
      "buyamount": "1164.00",
      "sellamount": "933.00",
      "pnl": "-231.00",
      "realised": "-231.00",
      "unrealised": "-0.00",
      "ltp": "20.15",
      "close": "41.15"
    },
    {
      "symboltoken": "67544",
      "symbolname": "BANKNIFTY",
      "instrumenttype": "OPTIDX",
      "priceden": "1.00",
      "pricenum": "1.00",
      "genden": "1.00",
      "gennum": "1.00",
      "precision": "2",
      "multiplier": "-1",
      "boardlotsize": "1",
      "exchange": "NFO",
      "producttype": "CARRYFORWARD",
      "tradingsymbol": "BANKNIFTY24APR2448900CE",
      "symbolgroup": "XX",
      "strikeprice": "48900.0",
      "optiontype": "CE",
      "expirydate": "24APR2024",
      "lotsize": "15",
      "cfbuyqty": "0",
      "cfsellqty": "0",
      "cfbuyamount": "0.00",
      "cfsellamount": "0.00",
      "buyavgprice": "16.20",
      "sellavgprice": "0.00",
      "avgnetprice": "16.20",
      "netvalue": "-1458.00",
      "netqty": "90",
      "totalbuyvalue": "1458.00",
      "totalsellvalue": "0.00",
      "cfbuyavgprice": "0.00",
      "cfsellavgprice": "0.00",
      "totalbuyavgprice": "16.20",
      "totalsellavgprice": "0.00",
      "netprice": "16.20",
      "buyqty": "90",
      "sellqty": "0",
      "buyamount": "1458.00",
      "sellamount": "0.00",
      "pnl": "0.00",
      "realised": "-0.00",
      "unrealised": "0.00",
      "ltp": "16.2",
      "close": "32.6"
    },
    {
      "symboltoken": "41094",
      "symbolname": "NIFTY",
      "instrumenttype": "OPTIDX",
      "priceden": "1.00",
      "pricenum": "1.00",
      "genden": "1.00",
      "gennum": "1.00",
      "precision": "2",
      "multiplier": "-1",
      "boardlotsize": "1",
      "exchange": "NFO",
      "producttype": "CARRYFORWARD",
      "tradingsymbol": "NIFTY02MAY2421950PE",
      "symbolgroup": "XX",
      "strikeprice": "21950.0",
      "optiontype": "PE",
      "expirydate": "02MAY2024",
      "lotsize": "50",
      "cfbuyqty": "0",
      "cfsellqty": "0",
      "cfbuyamount": "0.00",
      "cfsellamount": "0.00",
      "buyavgprice": "57.50",
      "sellavgprice": "0.00",
      "avgnetprice": "57.50",
      "netvalue": "-11500.00",
      "netqty": "200",
      "totalbuyvalue": "11500.00",
      "totalsellvalue": "0.00",
      "cfbuyavgprice": "0.00",
      "cfsellavgprice": "0.00",
      "totalbuyavgprice": "57.50",
      "totalsellavgprice": "0.00",
      "netprice": "57.50",
      "buyqty": "200",
      "sellqty": "0",
      "buyamount": "11500.00",
      "sellamount": "0.00",
      "pnl": "-1530.00",
      "realised": "-0.00",
      "unrealised": "-1530.00",
      "ltp": "49.85",
      "close": "136.7"
    },
    {
      "symboltoken": "41311",
      "symbolname": "NIFTY",
      "instrumenttype": "OPTIDX",
      "priceden": "1.00",
      "pricenum": "1.00",
      "genden": "1.00",
      "gennum": "1.00",
      "precision": "2",
      "multiplier": "-1",
      "boardlotsize": "1",
      "exchange": "NFO",
      "producttype": "CARRYFORWARD",
      "tradingsymbol": "NIFTY02MAY2422700CE",
      "symbolgroup": "XX",
      "strikeprice": "22700.0",
      "optiontype": "CE",
      "expirydate": "02MAY2024",
      "lotsize": "50",
      "cfbuyqty": "0",
      "cfsellqty": "0",
      "cfbuyamount": "0.00",
      "cfsellamount": "0.00",
      "buyavgprice": "62.65",
      "sellavgprice": "0.00",
      "avgnetprice": "62.65",
      "netvalue": "-12530.00",
      "netqty": "200",
      "totalbuyvalue": "12530.00",
      "totalsellvalue": "0.00",
      "cfbuyavgprice": "0.00",
      "cfsellavgprice": "0.00",
      "totalbuyavgprice": "62.65",
      "totalsellavgprice": "0.00",
      "netprice": "62.65",
      "buyqty": "200",
      "sellqty": "0",
      "buyamount": "12530.00",
      "sellamount": "0.00",
      "pnl": "1670.00",
      "realised": "-0.00",
      "unrealised": "1670.00",
      "ltp": "71.0",
      "close": "38.55"
    },
    {
      "symboltoken": "68091",
      "symbolname": "NIFTY",
      "instrumenttype": "OPTIDX",
      "priceden": "1.00",
      "pricenum": "1.00",
      "genden": "1.00",
      "gennum": "1.00",
      "precision": "2",
      "multiplier": "-1",
      "boardlotsize": "1",
      "exchange": "NFO",
      "producttype": "CARRYFORWARD",
      "tradingsymbol": "NIFTY25APR2422100PE",
      "symbolgroup": "XX",
      "strikeprice": "22100.0",
      "optiontype": "PE",
      "expirydate": "25APR2024",
      "lotsize": "50",
      "cfbuyqty": "0",
      "cfsellqty": "0",
      "cfbuyamount": "0.00",
      "cfsellamount": "0.00",
      "buyavgprice": "65.20",
      "sellavgprice": "41.17",
      "avgnetprice": "17.15",
      "netvalue": "3430.00",
      "netqty": "-200",
      "totalbuyvalue": "13040.00",
      "totalsellvalue": "16470.00",
      "cfbuyavgprice": "0.00",
      "cfsellavgprice": "0.00",
      "totalbuyavgprice": "65.20",
      "totalsellavgprice": "41.17",
      "netprice": "17.15",
      "buyqty": "200",
      "sellqty": "400",
      "buyamount": "13040.00",
      "sellamount": "16470.00",
      "pnl": "-2572.00",
      "realised": "-4806.00",
      "unrealised": "2234.00",
      "ltp": "30.0",
      "close": "146.75"
    },
    {
      "symboltoken": "68095",
      "symbolname": "NIFTY",
      "instrumenttype": "OPTIDX",
      "priceden": "1.00",
      "pricenum": "1.00",
      "genden": "1.00",
      "gennum": "1.00",
      "precision": "2",
      "multiplier": "-1",
      "boardlotsize": "1",
      "exchange": "NFO",
      "producttype": "CARRYFORWARD",
      "tradingsymbol": "NIFTY25APR2422200PE",
      "symbolgroup": "XX",
      "strikeprice": "22200.0",
      "optiontype": "PE",
      "expirydate": "25APR2024",
      "lotsize": "50",
      "cfbuyqty": "0",
      "cfsellqty": "0",
      "cfbuyamount": "0.00",
      "cfsellamount": "0.00",
      "buyavgprice": "63.45",
      "sellavgprice": "95.40",
      "avgnetprice": "0.00",
      "netvalue": "6390.00",
      "netqty": "0",
      "totalbuyvalue": "12690.00",
      "totalsellvalue": "19080.00",
      "cfbuyavgprice": "0.00",
      "cfsellavgprice": "0.00",
      "totalbuyavgprice": "63.45",
      "totalsellavgprice": "95.40",
      "netprice": "0.00",
      "buyqty": "200",
      "sellqty": "200",
      "buyamount": "12690.00",
      "sellamount": "19080.00",
      "pnl": "6390.00",
      "realised": "6390.00",
      "unrealised": "0.00",
      "ltp": "46.0",
      "close": "192.3"
    },
    {
      "symboltoken": "68108",
      "symbolname": "NIFTY",
      "instrumenttype": "OPTIDX",
      "priceden": "1.00",
      "pricenum": "1.00",
      "genden": "1.00",
      "gennum": "1.00",
      "precision": "2",
      "multiplier": "-1",
      "boardlotsize": "1",
      "exchange": "NFO",
      "producttype": "CARRYFORWARD",
      "tradingsymbol": "NIFTY25APR2422400CE",
      "symbolgroup": "XX",
      "strikeprice": "22400.0",
      "optiontype": "CE",
      "expirydate": "25APR2024",
      "lotsize": "50",
      "cfbuyqty": "0",
      "cfsellqty": "0",
      "cfbuyamount": "0.00",
      "cfsellamount": "0.00",
      "buyavgprice": "87.50",
      "sellavgprice": "71.85",
      "avgnetprice": "0.00",
      "netvalue": "-3130.00",
      "netqty": "0",
      "totalbuyvalue": "17500.00",
      "totalsellvalue": "14370.00",
      "cfbuyavgprice": "0.00",
      "cfsellavgprice": "0.00",
      "totalbuyavgprice": "87.50",
      "totalsellavgprice": "71.85",
      "netprice": "0.00",
      "buyqty": "200",
      "sellqty": "200",
      "buyamount": "17500.00",
      "sellamount": "14370.00",
      "pnl": "-3130.00",
      "realised": "-3130.00",
      "unrealised": "-0.00",
      "ltp": "109.65",
      "close": "46.7"
    },
    {
      "symboltoken": "68114",
      "symbolname": "NIFTY",
      "instrumenttype": "OPTIDX",
      "priceden": "1.00",
      "pricenum": "1.00",
      "genden": "1.00",
      "gennum": "1.00",
      "precision": "2",
      "multiplier": "-1",
      "boardlotsize": "1",
      "exchange": "NFO",
      "producttype": "CARRYFORWARD",
      "tradingsymbol": "NIFTY25APR2422500CE",
      "symbolgroup": "XX",
      "strikeprice": "22500.0",
      "optiontype": "CE",
      "expirydate": "25APR2024",
      "lotsize": "50",
      "cfbuyqty": "0",
      "cfsellqty": "0",
      "cfbuyamount": "0.00",
      "cfsellamount": "0.00",
      "buyavgprice": "40.00",
      "sellavgprice": "49.12",
      "avgnetprice": "58.25",
      "netvalue": "11650.00",
      "netqty": "-200",
      "totalbuyvalue": "8000.00",
      "totalsellvalue": "19650.00",
      "cfbuyavgprice": "0.00",
      "cfsellavgprice": "0.00",
      "totalbuyavgprice": "40.00",
      "totalsellavgprice": "49.12",
      "netprice": "58.25",
      "buyqty": "200",
      "sellqty": "400",
      "buyamount": "8000.00",
      "sellamount": "19650.00",
      "pnl": "-652.00",
      "realised": "1824.00",
      "unrealised": "-2476.00",
      "ltp": "61.5",
      "close": "25.7"
    }
  ]
}
